pygameeasy/__init__.py
pygameeasy/pygamee.py
pygameeasy-0.1.1.dist-info/licenses/license
pygameeasy-0.1.1.dist-info/METADATA
pygameeasy-0.1.1.dist-info/WHEEL
pygameeasy-0.1.1.dist-info/top_level.txt
pygameeasy-0.1.1.dist-info/RECORD
