Metadata-Version: 2.4
Name: pygameeasy
Version: 0.1.1
Summary: Assembly-like virtual CPU in Python
Author-email: Tamim Almutairi <3bth5550@gmail.com>
License-File: license
Dynamic: license-file
